umbraSnscrpe/__init__.py
umbraSnscrpe/_cli.py
umbraSnscrpe/base.py
umbraSnscrpe/version.py
umbraSnscrpe/modules/__init__.py
umbraSnscrpe/modules/facebook.py
umbraSnscrpe/modules/instagram.py
umbraSnscrpe/modules/mastodon.py
umbraSnscrpe/modules/reddit.py
umbraSnscrpe/modules/telegram.py
umbraSnscrpe/modules/twitter.py
umbraSnscrpe/modules/vkontakte.py
umbraSnscrpe/modules/weibo.py
umbraSenscraping-0.0.8.dist-info/LICENSE
umbraSenscraping-0.0.8.dist-info/METADATA
umbraSenscraping-0.0.8.dist-info/WHEEL
umbraSenscraping-0.0.8.dist-info/top_level.txt
umbraSenscraping-0.0.8.dist-info/RECORD
