Metadata-Version: 2.1
Name: umbraSenscraping
Version: 0.0.8
Summary: A social networking service scraper
Author-email: Ahmed Emad <ahmad.emad@umbrasys.com>
Classifier: Development Status :: 4 - Beta
Classifier: License :: OSI Approved :: GNU General Public License v3 or later (GPLv3+)
Classifier: Programming Language :: Python :: 3.8
Classifier: Programming Language :: Python :: 3.9
Classifier: Programming Language :: Python :: 3.10
Requires-Python: >=3.7
License-File: LICENSE
Requires-Dist: requests[socks]
Requires-Dist: lxml
Requires-Dist: beautifulsoup4
Requires-Dist: filelock
Requires-Dist: pytz ; python_version < "3.9.0"
